skymanager-1.0.1.dist-info/licenses/LICENSE
skymanagerapi/__init__.py
skymanagerapi/skymanagerapi.py
skymanager-1.0.1.dist-info/METADATA
skymanager-1.0.1.dist-info/WHEEL
skymanager-1.0.1.dist-info/help.txt
skymanager-1.0.1.dist-info/top_level.txt
skymanager-1.0.1.dist-info/RECORD
