Metadata-Version: 2.4
Name: skymanager
Version: 1.0.1
Summary: Asynchronous API of the SkyManager service
Author-email: Mits <mits.dev.tg@email.com>
License: This is free and unencumbered software released into the public domain.
Project-URL: Homepage, https://github.com/MitsCreator/SkyManagerAPI
Project-URL: Repository, https://github.com/MitsCreator/SkyManagerAPI
Project-URL: BugTracker, https://github.com/MitsCreator/SkyManagerAPI/issues
Project-URL: Documentation, https://skymanager.top/redoc
Keywords: python,skymanager,async,asyncio,cache
Classifier: Development Status :: 4 - Beta
Classifier: Intended Audience :: Developers
Classifier: Programming Language :: Python :: 3
Classifier: Operating System :: Unix
Classifier: Operating System :: MacOS :: MacOS X
Classifier: Operating System :: Microsoft :: Windows
Requires-Python: >=3.7
License-File: LICENSE
Requires-Dist: aiohttp
Requires-Dist: cachetools
Dynamic: license-file
